oarepo_doi/__init__.py
oarepo_doi/config.py
oarepo_doi/ext.py
oarepo_doi/__pycache__/__init__.cpython-312.pyc
oarepo_doi/__pycache__/config.cpython-312.pyc
oarepo_doi/__pycache__/ext.cpython-312.pyc
oarepo_doi/actions/__init__.py
oarepo_doi/actions/doi.py
oarepo_doi/actions/__pycache__/__init__.cpython-312.pyc
oarepo_doi/actions/__pycache__/doi.cpython-312.pyc
oarepo_doi/alembic/__init__.py
oarepo_doi/alembic/dbbeab0ad917_create_oarepo_doi_branch.py
oarepo_doi/alembic/settings_tables.py
oarepo_doi/notifications/__init__.py
oarepo_doi/notifications/__pycache__/__init__.cpython-312.pyc
oarepo_doi/notifications/builders/__init__.py
oarepo_doi/notifications/builders/assign_doi.py
oarepo_doi/notifications/builders/delete_doi.py
oarepo_doi/notifications/builders/__pycache__/__init__.cpython-312.pyc
oarepo_doi/notifications/builders/__pycache__/assign_doi.cpython-312.pyc
oarepo_doi/notifications/builders/__pycache__/delete_doi.cpython-312.pyc
oarepo_doi/services/__init__.py
oarepo_doi/services/doi_client.py
oarepo_doi/services/doi_provider.py
oarepo_doi/services/invenio_provider.py
oarepo_doi/services/relations.py
oarepo_doi/services/utils.py
oarepo_doi/services/__pycache__/__init__.cpython-312.pyc
oarepo_doi/services/__pycache__/doi_client.cpython-312.pyc
oarepo_doi/services/__pycache__/doi_provider.cpython-312.pyc
oarepo_doi/services/__pycache__/invenio_provider.cpython-312.pyc
oarepo_doi/services/__pycache__/relations.cpython-312.pyc
oarepo_doi/services/__pycache__/utils.cpython-312.pyc
oarepo_doi/services/components/__init__.py
oarepo_doi/settings/__init__.py
oarepo_doi/settings/api.py
oarepo_doi/settings/components.py
oarepo_doi/settings/facets.py
oarepo_doi/settings/models.py
oarepo_doi/settings/permissions.py
oarepo_doi/settings/proxies.py
oarepo_doi/settings/resource.py
oarepo_doi/settings/results.py
oarepo_doi/settings/schema.py
oarepo_doi/settings/service.py
oarepo_doi/settings/views.py
oarepo_doi/settings/__pycache__/__init__.cpython-312.pyc
oarepo_doi-3.0.1.dist-info/licenses/LICENSE
oarepo_doi-3.0.1.dist-info/METADATA
oarepo_doi-3.0.1.dist-info/WHEEL
oarepo_doi-3.0.1.dist-info/entry_points.txt
oarepo_doi-3.0.1.dist-info/top_level.txt
oarepo_doi-3.0.1.dist-info/RECORD
