Metadata-Version: 2.4
Name: oarepo-doi
Version: 3.0.1
Summary: "Oarepo12 DOI module with requests."
License-File: LICENSE
Requires-Dist: invenio-requests
Requires-Dist: oarepo-requests
Provides-Extra: dev
Requires-Dist: oarepo-tools; extra == "dev"
Provides-Extra: tests
Requires-Dist: oarepo-model-builder-tests; extra == "tests"
Requires-Dist: oarepo-requests; extra == "tests"
Requires-Dist: deepdiff; extra == "tests"
Requires-Dist: oarepo-ui; extra == "tests"
Requires-Dist: pytest-oarepo[requests]; extra == "tests"
Dynamic: license-file
